pagesource/__init__.py
pagesource/browser.py
pagesource/cli.py
pagesource/downloader.py
pagesource/utils.py
pagesource-0.1.2.dist-info/METADATA
pagesource-0.1.2.dist-info/WHEEL
pagesource-0.1.2.dist-info/entry_points.txt
pagesource-0.1.2.dist-info/licenses/LICENSE
pagesource-0.1.2.dist-info/RECORD
