Metadata-Version: 2.4
Name: pagesource
Version: 0.1.2
Summary: Capture all resources from a webpage like browser DevTools Sources tab
Project-URL: Homepage, https://github.com/timf34/pagesource
Project-URL: Repository, https://github.com/timf34/pagesource
Project-URL: Issues, https://github.com/timf34/pagesource/issues
Author-email: Tim Farrelly <timf34@gmail.com>
License-Expression: MIT
License-File: LICENSE
Keywords: cli,devtools,playwright,scraping,web
Classifier: Development Status :: 3 - Alpha
Classifier: Environment :: Console
Classifier: Intended Audience :: Developers
Classifier: License :: OSI Approved :: MIT License
Classifier: Programming Language :: Python :: 3
Classifier: Programming Language :: Python :: 3.10
Classifier: Programming Language :: Python :: 3.11
Classifier: Programming Language :: Python :: 3.12
Requires-Python: >=3.10
Requires-Dist: httpx>=0.25.0
Requires-Dist: playwright>=1.40.0
Requires-Dist: rich>=13.0.0
Requires-Dist: typer>=0.9.0
